proyecto1/gshare.v
module gshare
  #(
  parameter     HISTORY_SIZE  = 4
  )
 (
  input  clk_i,
  input  reset_i,
  input  branch_result, //Taken or Not taken.
  input  [31:0] next_PC, // Jump direction
  output prediction, //Take it or not take it.
  output [31:0] predicted_PC
 );

 integer i;
 
 reg [HISTORY_SIZE-1:0] global_history;
 reg [HISTORY_SIZE-1:0] global_history_prev;
 //00 WN
 //01 SN
 //10 WT
 //11 ST
 reg [1:0] pattern_history [0:2**(HISTORY_SIZE)-1]; 
 reg [31:0] PC_prediction [0:2**(HISTORY_SIZE)-1];
 reg prediction;
 reg [31:0] predicted_PC;
 
 always @(posedge clk_i) begin
  if (reset_i) begin
    global_history = 0;
    global_history_prev = 0;
  end
  else begin
    //global_history = {branch_result,global_history[HISTORY_SIZE-1:1]};
    global_history_prev = global_history;
    global_history = global_history >>1;
    global_history[HISTORY_SIZE-1] = branch_result;
  end
end 

always @(posedge clk_i) begin
    prediction = pattern_history[global_history][1];
    predicted_PC = PC_prediction[global_history];
end

always @(posedge clk_i) begin
  if (reset_i) begin
    for (i = 0; i < 2**HISTORY_SIZE; i = i + 1) begin
      pattern_history[i] = 1;
      PC_prediction[i] = 0;
    end
  end
  else begin
      if (branch_result == 1 && pattern_history[global_history_prev] != 11) begin
          pattern_history[global_history_prev] = pattern_history[global_history_prev] + 1;
          PC_prediction[global_history_prev] = next_PC;  //guardar PC_next solo en el caso Taken.
      end
      if (branch_result == 0 && pattern_history[global_history_prev] != 00)
        pattern_history[global_history_prev] = pattern_history[global_history_prev] - 1;
  end
end

endmodule

 //00 SN
 //01 WN
 //10 WT
 //11 ST

// Testbench Code Goes here
module gshare_tb;

reg clock, reset, branch;
reg [31:0] addr;

integer i;
parameter     HISTORY_SIZE  = 4;
  
initial begin

  $dumpfile("test.vcd");
  $dumpvars(0);

  for (i = 0; i < 2**HISTORY_SIZE; i = i + 1) $dumpvars(0, U0.pattern_history[i]); 
  
  clock = 0;
  reset = 0;
  #5 reset = 1;
  #15 reset = 0;
  branch=0;
  #1000
  $finish;
end

always @(posedge clock) begin
  branch = $random;
  addr = $random;
end
  
always begin
 #5 clock = !clock;
end

gshare U0 (
.clk_i (clock),
.reset_i (reset),
.branch_result (branch),
.predicted_PC (),
.next_PC (addr)
);


endmodule

proyecto1/test.vcd
$date
	Fri May  7 22:57:33 2021
$end
$version
	Icarus Verilog
$end
$timescale
	1s
$end
$scope module gshare_tb $end
$var reg 32 ! addr [31:0] $end
$var reg 1 " branch $end
$var reg 1 # clock $end
$var reg 1 $ reset $end
$var integer 32 % i [31:0] $end
$scope module U0 $end
$var wire 1 " branch_result $end
$var wire 1 # clk_i $end
$var wire 32 & next_PC [31:0] $end
$var wire 1 $ reset_i $end
$var reg 4 ' global_history [3:0] $end
$var reg 4 ( global_history_prev [3:0] $end
$var reg 32 ) predicted_PC [31:0] $end
$var reg 1 * prediction $end
$var integer 32 + i [31:0] $end
$upscope $end
$upscope $end
$scope module gshare_tb $end
$scope module U0 $end
$var reg 2 , \pattern_history[0] [1:0] $end
$upscope $end
$upscope $end
$scope module gshare_tb $end
$scope module U0 $end
$var reg 2 - \pattern_history[1] [1:0] $end
$upscope $end
$upscope $end
$scope module gshare_tb $end
$scope module U0 $end
$var reg 2 . \pattern_history[2] [1:0] $end
$upscope $end
$upscope $end
$scope module gshare_tb $end
$scope module U0 $end
$var reg 2 / \pattern_history[3] [1:0] $end
$upscope $end
$upscope $end
$scope module gshare_tb $end
$scope module U0 $end
$var reg 2 0 \pattern_history[4] [1:0] $end
$upscope $end
$upscope $end
$scope module gshare_tb $end
$scope module U0 $end
$var reg 2 1 \pattern_history[5] [1:0] $end
$upscope $end
$upscope $end
$scope module gshare_tb $end
$scope module U0 $end
$var reg 2 2 \pattern_history[6] [1:0] $end
$upscope $end
$upscope $end
$scope module gshare_tb $end
$scope module U0 $end
$var reg 2 3 \pattern_history[7] [1:0] $end
$upscope $end
$upscope $end
$scope module gshare_tb $end
$scope module U0 $end
$var reg 2 4 \pattern_history[8] [1:0] $end
$upscope $end
$upscope $end
$scope module gshare_tb $end
$scope module U0 $end
$var reg 2 5 \pattern_history[9] [1:0] $end
$upscope $end
$upscope $end
$scope module gshare_tb $end
$scope module U0 $end
$var reg 2 6 \pattern_history[10] [1:0] $end
$upscope $end
$upscope $end
$scope module gshare_tb $end
$scope module U0 $end
$var reg 2 7 \pattern_history[11] [1:0] $end
$upscope $end
$upscope $end
$scope module gshare_tb $end
$scope module U0 $end
$var reg 2 8 \pattern_history[12] [1:0] $end
$upscope $end
$upscope $end
$scope module gshare_tb $end
$scope module U0 $end
$var reg 2 9 \pattern_history[13] [1:0] $end
$upscope $end
$upscope $end
$scope module gshare_tb $end
$scope module U0 $end
$var reg 2 : \pattern_history[14] [1:0] $end
$upscope $end
$upscope $end
$scope module gshare_tb $end
$scope module U0 $end
$var reg 2 ; \pattern_history[15] [1:0] $end
$upscope $end
$upscope $end
$enddefinitions $end
#0
$dumpvars
bx ;
bx :
bx 9
bx 8
bx 7
bx 6
bx 5
bx 4
bx 3
bx 2
bx 1
bx 0
bx /
bx .
bx -
bx ,
bx +
x*
bx )
bx (
bx '
bx &
b10000 %
0$
0#
x"
bx !
$end
#5
b0 (
b0 '
b1 ;
b1 :
b1 9
b1 8
b1 7
b1 6
b1 5
b1 4
b1 3
b1 2
b1 1
b1 0
b1 /
b1 .
b1 -
b1 ,
b10000 +
b11000000100010010101111010000001 !
b11000000100010010101111010000001 &
0"
1#
1$
#10
0#
#15
b10110001111100000101011001100011 !
b10110001111100000101011001100011 &
1"
b1 ;
b1 :
b1 9
b1 8
b1 7
b1 6
b1 5
b1 4
b1 3
b1 2
b1 1
b1 0
b1 /
b1 .
b1 -
b1 ,
b10000 +
b0 )
0*
1#
#20
0#
0"
0$
#25
b1000 '
b1000110110111111001100110001101 )
1*
b10 ,
b1000110110111111001100110001101 !
b1000110110111111001100110001101 &
1"
1#
#30
0#
#35
b10001001001101110101001000010010 !
b10001001001101110101001000010010 &
b10 4
b0 )
0*
b1100 '
b1000 (
1#
#40
0#
#45
b1110 '
b1100 (
b11 4
b110110101111100110100001101 !
b110110101111100110100001101 &
1#
#50
0#
#55
b11110100011011100110100111101 !
b11110100011011100110100111101 &
0"
b10 :
b1111 '
b1110 (
1#
#60
0#
#65
b1111 '
b1111 (
b11 :
b1000110001011011111011110001100 !
b1000110001011011111011110001100 &
1"
1#
#70
0#
#75
b11100011001101110010010011000110 !
b11100011001101110010010011000110 &
b10 ;
b1111 '
1#
#80
0#
#85
b1111 '
b11010101000100111101001010101010 )
1*
b11 ;
b11010101000100111101001010101010 !
b11010101000100111101001010101010 &
1#
#90
0#
#95
b10111011110100100111001001110111 !
b10111011110100100111001001110111 &
b0 ;
b1111 '
1#
#100
0#
#105
b111 '
0*
b1000111111011001101101110001111 !
b1000111111011001101101110001111 &
0"
1#
#110
0#
#115
b11100111011101101001011011001110 !
b11100111011101101001011011001110 &
b0 3
b0 )
b11 '
b111 (
1#
#120
0#
#125
b1 '
b11 (
b11100010110010100100111011000101 !
b11100010110010100100111011000101 &
1#
#130
0#
#135
b11011110100011100010100010111101 !
b11011110100011100010100010111101 &
b0 -
b1000110110111111001100110001101 )
1*
b0 '
b1 (
1#
#140
0#
#145
b1000 '
b0 (
b1 -
b10110010101001110010011001100101 !
b10110010101001110010011001100101 &
1"
1#
#150
0#
#155
b101011100111000011100001010 !
b101011100111000011100001010 &
b0 4
b0 )
0*
b1100 '
b1000 (
1#
#160
0#
#165
b110 '
b1100 (
b10000011001000010000100100000 !
b10000011001000010000100100000 &
0"
1#
#170
0#
#175
b11001110110011001100110010011101 !
b11001110110011001100110010011101 &
b0 2
b11 '
b110 (
1#
#180
0#
#185
b1 '
b11 (
b10001001100000111011100000010011 !
b10001001100000111011100000010011 &
1#
#190
0#
#195
b10101001101001111101011001010011 !
b10101001101001111101011001010011 &
1"
b0 -
b1000110110111111001100110001101 )
1*
b0 '
b1 (
1#
#200
0#
#205
b1000 '
b0 (
b1 -
b11101010101001100010101011010101 !
b11101010101001100010101011010101 &
1#
#210
0#
#215
b11010111010101100011111010101110 !
b11010111010101100011111010101110 &
0"
b1 4
b0 )
0*
b1100 '
b1000 (
1#
#220
0#
#225
b1110 '
b1100 (
b10 4
b11100111110001010111001011001111 !
b11100111110001010111001011001111 &
1"
1#
#230
0#
#235
b101000010010110010100001010 !
b101000010010110010100001010 &
b0 :
b11010101000100111101001010101010 )
b1111 '
b1110 (
1#
#240
0#
#245
b111 '
b1111 (
b10011110001100010100110000111100 !
b10011110001100010100110000111100 &
0"
1#
#250
0#
#255
b1000101001011100110000110001010 !
b1000101001011100110000110001010 &
b0 )
b11 '
b111 (
1#
#260
0#
#265
b1001 '
b11 (
b1 3
b11101100010010110011010011011000 !
b11101100010010110011010011011000 &
1"
1#
#270
0#
#275
b11000100100010100001001010001001 !
b11000100100010100001001010001001 &
0"
b10 5
b1100 '
b1001 (
1#
#280
0#
#285
b1110 '
b1100 (
b11 5
b1011011000000100110010110110110 !
b1011011000000100110010110110110 &
1"
1#
#290
0#
#295
b1010111000101010001001110101110 !
b1010111000101010001001110101110 &
0"
b1 :
b11010101000100111101001010101010 )
b1111 '
b1110 (
1#
#300
0#
#305
b111 '
b1111 (
b0 :
b10101000011111101110100101010 !
b10101000011111101110100101010 &
1#
#310
0#
#315
b10111000100101111011111001110001 !
b10111000100101111011111001110001 &
1"
b0 3
b0 )
b11 '
b111 (
1#
#320
0#
#325
b1001 '
b11 (
b1 3
b100111111100100101010101001111 !
b100111111100100101010101001111 &
1#
#330
0#
#335
b11101000001100011001100111010 !
b11101000001100011001100111010 &
b0 5
b1100 '
b1001 (
1#
#340
0#
#345
b110 '
b1100 (
b1010101010100100101100010101 !
b1010101010100100101100010101 &
0"
1#
#350
0#
#355
b1101100100111000100101111011001 !
b1101100100111000100101111011001 &
1"
b11 '
b110 (
1#
#360
0#
#365
b1 '
b11 (
b100110001101011111101101001100 !
b100110001101011111101101001100 &
0"
1#
#370
0#
#375
b1000111101110011010000110001111 !
b1000111101110011010000110001111 &
1"
b0 -
b1000110110111111001100110001101 )
1*
b0 '
b1 (
1#
#380
0#
#385
b0 (
b11011011110011010110000010110111 !
b11011011110011010110000010110111 &
0"
1#
#390
0#
#395
b10101110011111011001010001011100 !
b10101110011111011001010001011100 &
1"
b1 ,
1#
#400
0#
#405
b1000 '
b1000100110111100011011110001001 )
b10 ,
b1000100110111100011011110001001 !
b1000100110111100011011110001001 &
1#
#410
0#
#415
b11101000001000110011111011010000 !
b11101000001000110011111011010000 &
b11 4
b0 )
0*
b1100 '
b1000 (
1#
#420
0#
#425
b1110 '
b1100 (
b0 4
b10101000110001111111110001010001 !
b10101000110001111111110001010001 &
1#
#430
0#
#435
b110000111010111111100001100 !
b110000111010111111100001100 &
0"
b1 :
b11010101000100111101001010101010 )
b1111 '
b1110 (
1#
#440
0#
#445
b111 '
b1111 (
b0 :
b1100100010101111110110111001000 !
b1100100010101111110110111001000 &
1#
#450
0#
#455
b11110111100101110110100111101 !
b11110111100101110110100111101 &
1"
b0 3
b0 )
b11 '
b111 (
1#
#460
0#
#465
b1 '
b11 (
b10111111000001010000000001111110 !
b10111111000001010000000001111110 &
0"
1#
#470
0#
#475
b11100110110011110011100111001 !
b11100110110011110011100111001 &
1"
b1000100110111100011011110001001 )
1*
b0 '
b1 (
1#
#480
0#
#485
b1000 '
b0 (
b1 -
b11101001111010111111011011010011 !
b11101001111010111111011011010011 &
1#
#490
0#
#495
b10111100000101001000100001111000 !
b10111100000101001000100001111000 &
b1 4
b0 )
0*
b1100 '
b1000 (
1#
#500
0#
#505
b1110 '
b1100 (
b10 4
b100100100010110100101101001001 !
b100100100010110100101101001001 &
1#
#510
0#
#515
b10101000011001010111100101010 !
b10101000011001010111100101010 &
b1 :
b11010101000100111101001010101010 )
b1111 '
b1110 (
1#
#520
0#
#525
b111 '
b1111 (
b0 :
b11000011001111110011100010000110 !
b11000011001111110011100010000110 &
0"
1#
#530
0#
#535
b11001110001011111111001010011100 !
b11001110001011111111001010011100 &
b0 )
b11 '
b111 (
1#
#540
0#
#545
b1 '
b11 (
b10010011011111011011110000100110 !
b10010011011111011011110000100110 &
1#
#550
0#
#555
b11010001100010111011010010100011 !
b11010001100010111011010010100011 &
1"
b0 -
b1000100110111100011011110001001 )
1*
b0 '
b1 (
1#
#560
0#
#565
b1000 '
b0 (
b1 -
b11011001110100101001001010110011 !
b11011001110100101001001010110011 &
1#
#570
0#
#575
b100010001010010000110101000100 !
b100010001010010000110101000100 &
b11 4
b0 )
0*
b1100 '
b1000 (
1#
#580
0#
#585
b1110 '
b1100 (
b0 4
b11100101100110110011011011001011 !
b11100101100110110011011011001011 &
1#
#590
0#
#595
b101101001010001101101101011010 !
b101101001010001101101101011010 &
0"
b1 :
b11010101000100111101001010101010 )
b1111 '
b1110 (
1#
#600
0#
#605
b1111 '
b1111 (
b10 :
b11110110100000101110001011101101 !
b11110110100000101110001011101101 &
1"
1#
#610
0#
#615
b10110010100111111011011001100101 !
b10110010100111111011011001100101 &
0"
b1 ;
b1111 '
1#
#620
0#
#625
b1111 '
b11101111101111101001010011011111 )
1*
b10 ;
b11101111101111101001010011011111 !
b11101111101111101001010011011111 &
1"
1#
#630
0#
#635
b100010001100011111111101000100 !
b100010001100011111111101000100 &
b11 ;
b1111 '
1#
#640
0#
#645
b111 '
b10 ;
b10101000010010000101100101010 !
b10101000010010000101100101010 &
0"
1#
#650
0#
#655
b111011011111100111100001110 !
b111011011111100111100001110 &
1"
b0 )
0*
b11 '
b111 (
1#
#660
0#
#665
b1 '
b11 (
b11001101010111101011110010011010 !
b11001101010111101011110010011010 &
0"
1#
#670
0#
#675
b11100001111100010000001011000011 !
b11100001111100010000001011000011 &
1"
b0 -
b1000100110111100011011110001001 )
1*
b0 '
b1 (
1#
#680
0#
#685
b0 (
b100111011110011110100101001110 !
b100111011110011110100101001110 &
0"
1#
#690
0#
#695
b10000101001100010011010000001010 !
b10000101001100010011010000001010 &
1"
b1 ,
1#
#700
0#
#705
0*
b0 ,
b10011100000011101000101000111000 !
b10011100000011101000101000111000 &
0"
1#
#710
0#
#715
b11011100001010111100010010111000 !
b11011100001010111100010010111000 &
1"
1#
#720
0#
#725
b1001001110001100101110110010011 !
b1001001110001100101110110010011 &
0"
1#
#730
0#
#735
b10101100101101111100101001011001 !
b10101100101101111100101001011001 &
1#
#740
0#
#745
b1000 '
b10100110111111001101111001001101 )
b1 ,
b10100110111111001101111001001101 !
b10100110111111001101111001001101 &
1"
1#
#750
0#
#755
b10110110101001000010011001101101 !
b10110110101001000010011001101101 &
b1 4
b0 )
b1100 '
b1000 (
1#
#760
0#
#765
b110 '
b1100 (
b0 4
b1100101001110110100100111001010 !
b1100101001110110100100111001010 &
0"
1#
#770
0#
#775
b1001010100100110111000110010101 !
b1001010100100110111000110010101 &
b11 '
b110 (
1#
#780
0#
#785
b1 '
b11 (
b10011101001001101100000100 !
b10011101001001101100000100 &
1#
#790
0#
#795
b110100100110000000011101101001 !
b110100100110000000011101101001 &
1"
b10100110111111001101111001001101 )
b0 '
b1 (
1#
#800
0#
#805
b0 (
b1000100000000011000110110001000 !
b1000100000000011000110110001000 &
0"
1#
#810
0#
#815
b10010110100100000000010000101101 !
b10010110100100000000010000101101 &
b0 ,
1#
#820
0#
#825
b1000 '
b10010111010111001001110000101110 )
b1 ,
b10010111010111001001110000101110 !
b10010111010111001001110000101110 &
1"
1#
#830
0#
#835
b1110010000010100010100011100 !
b1110010000010100010100011100 &
0"
b1 4
b0 )
b1100 '
b1000 (
1#
#840
0#
#845
b1110 '
b1100 (
b10 4
b10100100111100000011100101001 !
b10100100111100000011100101001 &
1"
1#
#850
0#
#855
b1000011001101010110011110000110 !
b1000011001101010110011110000110 &
0"
b11 :
b11101111101111101001010011011111 )
1*
b1111 '
b1110 (
1#
#860
0#
#865
b111 '
b1111 (
b10 :
b10011110101101111100011000111101 !
b10011110101101111100011000111101 &
1#
#870
0#
#875
b10111000010101011100010001110000 !
b10111000010101011100010001110000 &
b0 )
0*
b11 '
b111 (
1#
#880
0#
#885
b1001 '
b11 (
b1 3
b1011101011100011001100110111010 !
b1011101011100011001100110111010 &
1"
1#
#890
0#
#895
b1111101010001110111100111111010 !
b1111101010001110111100111111010 &
0"
b1 5
b1100 '
b1001 (
1#
#900
0#
#905
b1110 '
b1100 (
b10 5
b10001101001001001111011000011010 !
b10001101001001001111011000011010 &
1"
1#
#910
0#
#915
b11011100001110110000100110111 !
b11011100001110110000100110111 &
b11 :
b11101111101111101001010011011111 )
1*
b1111 '
b1110 (
1#
#920
0#
#925
b111 '
b1111 (
b10 :
b1100000001110010010000111000000 !
b1100000001110010010000111000000 &
0"
1#
#930
0#
#935
b11011011010001100001101010110110 !
b11011011010001100001101010110110 &
b0 3
b0 )
0*
b11 '
b111 (
1#
#940
0#
#945
b1001 '
b11 (
b1 3
b1101110010111110000111111011100 !
b1101110010111110000111111011100 &
1"
1#
#950
0#
#955
b111100000000111111111101111000 !
b111100000000111111111101111000 &
0"
b11 5
b1100 '
b1001 (
1#
#960
0#
#965
b110 '
b1100 (
b10 5
b11101101100011011000000011011011 !
b11101101100011011000000011011011 &
1#
#970
0#
#975
b111100111011010010101101111001 !
b111100111011010010101101111001 &
1"
b11 '
b110 (
1#
#980
0#
#985
b1 '
b11 (
b10110000101111001110111001100001 !
b10110000101111001110111001100001 &
0"
1#
#990
0#
#995
b11010000111101010111100010100001 !
b11010000111101010111100010100001 &
1"
b10010111010111001001110000101110 )
b0 '
b1 (
1#
#1000
0#
#1005
b0 (
b10101000011000111001011001010000 !
b10101000011000111001011001010000 &
0"
1#
#1010
0#
#1015
b10011010101101001000100000110101 !
b10011010101101001000100000110101 &
1"
b0 ,
1#
